streamkeeper/__init__.py
streamkeeper/services/ConversionService.py
streamkeeper/services/NotificationService.py
streamkeeper/services/StreamDiscoveryService.py
streamkeeper/services/StreamDownloadService.py
streamkeeper/services/__init__.py
streamkeeper/streamkeeper.py
streamkeeper-2.0.1.dist-info/entry_points.txt
streamkeeper-2.0.1.dist-info/WHEEL
streamkeeper-2.0.1.dist-info/METADATA
streamkeeper-2.0.1.dist-info/RECORD
